MANIFEST.in
README.rst
README.txt
setup.py
docs/HISTORY.txt
docs/LICENSE.GPL
docs/LICENSE.txt
edw/__init__.py
edw.userhistory.egg-info/PKG-INFO
edw.userhistory.egg-info/SOURCES.txt
edw.userhistory.egg-info/dependency_links.txt
edw.userhistory.egg-info/entry_points.txt
edw.userhistory.egg-info/namespace_packages.txt
edw.userhistory.egg-info/not-zip-safe
edw.userhistory.egg-info/requires.txt
edw.userhistory.egg-info/top_level.txt
edw/userhistory/__init__.py
edw/userhistory/configure.zcml
edw/userhistory/events.py
edw/userhistory/version.txt
edw/userhistory/browser/__init__.py
edw/userhistory/browser/configure.zcml
edw/userhistory/browser/userhistory.py
edw/userhistory/browser/userlisthistory.py
edw/userhistory/browser/templates/userhistory.pt
edw/userhistory/browser/templates/userlisthistory.pt
edw/userhistory/docs/portlet.txt
edw/userhistory/portlets/__init__.py
edw/userhistory/portlets/configure.zcml
edw/userhistory/portlets/userhistory.pt
edw/userhistory/portlets/userhistory.py
edw/userhistory/profiles/default/controlpanel.xml
edw/userhistory/profiles/default/metadata.xml
edw/userhistory/profiles/default/portlets.xml
edw/userhistory/tests/__init__.py
edw/userhistory/tests/base.py
edw/userhistory/tests/test_doctests.py