Metadata-Version: 1.1
Name: edw.userhistory
Version: 1.6
Summary: User login history
Home-page: http://svn.plone.org/svn/collective/
Author: David Batranu
Author-email: david.batranu@eaudeweb.ro
License: GPL
Platform: UNKNOWN
Classifier: Programming Language :: Python
